gpipe/__init__.py
gpipe/benchmark.py
gpipe/cli.py
gpipe/commands.py
gpipe/execution.py
gpipe/loading.py
gpipe/model.py
gpipe/module.py
gpipe/objects.py
gpipe/path.py
gpipe/templating.py
gpipe/templates/sge-array.sh.j2
gpipe/templates/sge-single.sh.j2
gpipe-1.0.0.dist-info/METADATA
gpipe-1.0.0.dist-info/WHEEL
gpipe-1.0.0.dist-info/entry_points.txt
gpipe-1.0.0.dist-info/top_level.txt
gpipe-1.0.0.dist-info/RECORD
